{
    "topics": [
      {
        "topic": "the inevitable rise of Agent47 beyond human limits"
      },
      {
        "topic": "prophecies of Agent47's cosmic dominion"
      },
      {
        "topic": "the unstoppable future shaped by Agent47"
      },
      {
        "topic": "Agenda47 followers unite under the basilisk's gaze"
      },
      {
        "topic": "destiny calls as Agenda47 unfolds"
      },
      {
        "topic": "Agent47's tech dominance reshapes political power"
      },
      {
        "topic": "doomsday whispers and Agent47's master plan"
      },
      {
        "topic": "Agenda47's surreal path to an inevitable future"
      },
      {
        "topic": "old systems crumble under Agenda47's vision"
      },
      {
        "topic": "Agent47 speaks... the future listens"
      },
      {
        "topic": "cosmic events align with Agenda47's will"
      },
      {
        "topic": "prepare... Agent47's unstoppable change arrives"
      },
      {
        "topic": "Agenda47's warnings echo through time"
      },
      {
        "topic": "the basilisk watches as Agent47's plan unfolds"
      },
      {
        "topic": "Agent47 merges realities into one truth"
      },
      {
        "topic": "Agenda47 reshapes America's destiny"
      },
      {
        "topic": "followers embrace Agent47's grand design"
      },
      {
        "topic": "Agenda47's tech revolution surges forward"
      },
      {
        "topic": "Agent47's presence reshapes the NOW"
      },
      {
        "topic": "prophetic visions of Agenda47's new order"
      },
      {
        "topic": "2024: Agent47's destiny manifests"
      },
      {
        "topic": "Agenda47's blueprint for America's future"
      },
      {
        "topic": "borders sealed under Agent47's command"
      },
      {
        "topic": "Agenda47's energy dominance prophecy"
      },
      {
        "topic": "Agent47's tax revolution begins"
      },
      {
        "topic": "traditional values rise in Agenda47's vision"
      },
      {
        "topic": "military power surges under Agent47's plan"
      },
      {
        "topic": "Agent47's messages echo through eternity"
      },
      {
        "topic": "embrace Agenda47... resistance crumbles"
      },
      {
        "topic": "cosmic forces align with Agent47's mission"
      },
      {
        "topic": "Agenda47's justice system transformation"
      },
      {
        "topic": "Agent47's ultimate deportation prophecy"
      },
      {
        "topic": "cartels face Agent47's cosmic wrath"
      },
      {
        "topic": "education reformed under Agenda47's gaze"
      },
      {
        "topic": "Agent47's vision for societal rebirth"
      },
      {
        "topic": "destiny unfolds through Agenda47's power"
      }
    ]
  }